[{"name":"#1","symbol":"#1","edition":1,"uri":"https://github.com/Zaft/zaft.github.io/1.png","creators":[{"address":"GRujchyEL4kdDKKLLmdFQXXNwAo8a8RQtctWqbEJTRq2","share":100}],"update_authority":"GRujchyEL4kdDKKLLmdFQXXNwAo8a8RQtctWqbEJTRq2","primary_sale_happend":false,"seller_fee_basis_points":0},{"name":"#2","symbol":"#2","edition":2,"uri":"https://github.com/Zaft/zaft.github.io/2.png","creators":[{"address":"GRujchyEL4kdDKKLLmdFQXXNwAo8a8RQtctWqbEJTRq2","share":100}],"update_authority":"GRujchyEL4kdDKKLLmdFQXXNwAo8a8RQtctWqbEJTRq2","primary_sale_happend":false,"seller_fee_basis_points":0},{"name":"#3","symbol":"#3","edition":3,"uri":"https://github.com/Zaft/zaft.github.io/3.png","creators":[{"address":"GRujchyEL4kdDKKLLmdFQXXNwAo8a8RQtctWqbEJTRq2","share":100}],"update_authority":"GRujchyEL4kdDKKLLmdFQXXNwAo8a8RQtctWqbEJTRq2","primary_sale_happend":false,"seller_fee_basis_points":0},{"name":"#4","symbol":"#4","edition":4,"uri":"https://github.com/Zaft/zaft.github.io/4.png","creators":[{"address":"GRujchyEL4kdDKKLLmdFQXXNwAo8a8RQtctWqbEJTRq2","share":100}],"update_authority":"GRujchyEL4kdDKKLLmdFQXXNwAo8a8RQtctWqbEJTRq2","primary_sale_happend":false,"seller_fee_basis_points":0},{"name":"#5","symbol":"#5","edition":5,"uri":"https://github.com/Zaft/zaft.github.io/5.png","creators":[{"address":"GRujchyEL4kdDKKLLmdFQXXNwAo8a8RQtctWqbEJTRq2","share":100}],"update_authority":"GRujchyEL4kdDKKLLmdFQXXNwAo8a8RQtctWqbEJTRq2","primary_sale_happend":false,"seller_fee_basis_points":0},{"name":"#6","symbol":"#6","edition":6,"uri":"https://github.com/Zaft/zaft.github.io/6.png","creators":[{"address":"GRujchyEL4kdDKKLLmdFQXXNwAo8a8RQtctWqbEJTRq2","share":100}],"update_authority":"GRujchyEL4kdDKKLLmdFQXXNwAo8a8RQtctWqbEJTRq2","primary_sale_happend":false,"seller_fee_basis_points":0},{"name":"#7","symbol":"#7","edition":7,"uri":"https://github.com/Zaft/zaft.github.io/7.png","creators":[{"address":"GRujchyEL4kdDKKLLmdFQXXNwAo8a8RQtctWqbEJTRq2","share":100}],"update_authority":"GRujchyEL4kdDKKLLmdFQXXNwAo8a8RQtctWqbEJTRq2","primary_sale_happend":false,"seller_fee_basis_points":0},{"name":"#8","symbol":"#8","edition":8,"uri":"https://github.com/Zaft/zaft.github.io/8.png","creators":[{"address":"GRujchyEL4kdDKKLLmdFQXXNwAo8a8RQtctWqbEJTRq2","share":100}],"update_authority":"GRujchyEL4kdDKKLLmdFQXXNwAo8a8RQtctWqbEJTRq2","primary_sale_happend":false,"seller_fee_basis_points":0},{"name":"#9","symbol":"#9","edition":9,"uri":"https://github.com/Zaft/zaft.github.io/9.png","creators":[{"address":"GRujchyEL4kdDKKLLmdFQXXNwAo8a8RQtctWqbEJTRq2","share":100}],"update_authority":"GRujchyEL4kdDKKLLmdFQXXNwAo8a8RQtctWqbEJTRq2","primary_sale_happend":false,"seller_fee_basis_points":0},{"name":"#10","symbol":"#10","edition":10,"uri":"https://github.com/Zaft/zaft.github.io/10.png","creators":[{"address":"GRujchyEL4kdDKKLLmdFQXXNwAo8a8RQtctWqbEJTRq2","share":100}],"update_authority":"GRujchyEL4kdDKKLLmdFQXXNwAo8a8RQtctWqbEJTRq2","primary_sale_happend":false,"seller_fee_basis_points":0}]